DSSE/__init__.py
DSSE/environment/__init__.py
DSSE/environment/constants.py
DSSE/environment/coverage_env.py
DSSE/environment/env.py
DSSE/environment/env_base.py
DSSE/environment/pygame_interface.py
DSSE/environment/entities/__init__.py
DSSE/environment/entities/drone.py
DSSE/environment/entities/person.py
DSSE/environment/imgs/__init__.py
DSSE/environment/imgs/drone.png
DSSE/environment/imgs/person-swimming.png
DSSE/environment/simulation/__init__.py
DSSE/environment/simulation/dynamic_probability.py
DSSE/environment/simulation/particle_simulation.py
DSSE/environment/simulation/time_step.py
DSSE/environment/wrappers/__init__.py
DSSE/environment/wrappers/all_flatten_wrapper.py
DSSE/environment/wrappers/all_positions_wrapper.py
DSSE/environment/wrappers/communication_wrapper.py
DSSE/environment/wrappers/gaussian_wrapper.py
DSSE/environment/wrappers/matrix_encode_wrapper.py
DSSE/environment/wrappers/retain_drone_pos_wrapper.py
DSSE/environment/wrappers/top_n_cells_wrapper.py
DSSE/tests/__init__.py
DSSE/tests/drone_policy.py
DSSE/tests/test_env.py
DSSE/tests/test_env_coverage.py
DSSE/tests/test_matrix.py
DSSE-1.1.9.dist-info/LICENSE
DSSE-1.1.9.dist-info/METADATA
DSSE-1.1.9.dist-info/WHEEL
DSSE-1.1.9.dist-info/top_level.txt
DSSE-1.1.9.dist-info/RECORD
