Metadata-Version: 2.1
Name: DSSE
Version: 1.1.9
Summary: The Drone Swarm Search project provides an environment for SAR missions built on PettingZoo, where agents, represented by drones, are tasked with locating targets identified as shipwrecked individuals.
Download-URL: https://github.com/pfeinsper/drone-swarm-search/archive/refs/tags/1.1.9.tar.gz
Author: Luis Filipe Carrete, Manuel Castanares, Enrico Damiani, Leonardo Malta
Author-email: Ricardo Ribeiro Rodrigues <ricardorr7@al.insper.edu.br>, Renato Laffranchi Falcão <renatolf1@al.insper.edu.br>, Pedro Henrique Britto Aragão Andrade <pedroa3@al.insper.edu.br>, Jorás Oliveira <jorascco@al.insper.edu.br>, Fabricio Barth <fabriciojb@insper.edu.br>
License: MIT License
Project-URL: Homepage, https://pfeinsper.github.io/drone-swarm-search/
Project-URL: Repository, https://github.com/pfeinsper/drone-swarm-search/
Project-URL: Documentation, https://pfeinsper.github.io/drone-swarm-search/
Project-URL: Bug Report, https://github.com/pfeinsper/drone-swarm-search/issues/
Keywords: Reinforcement Learning,AI,SAR,Multi Agent Reinforcement Learning
Classifier: Development Status :: 4 - Beta
Classifier: Programming Language :: Python :: 3.10
Classifier: Programming Language :: Python :: 3.11
Classifier: Intended Audience :: Science/Research
Classifier: Topic :: Scientific/Engineering :: Artificial Intelligence
Requires-Python: >=3.10.5
License-File: LICENSE
Requires-Dist: numpy >=1.23.1
Requires-Dist: gymnasium >=0.27.1
Requires-Dist: pygame >=2.3.0
Requires-Dist: pettingzoo >=1.22.3
Requires-Dist: matplotlib ==3.8.4
Requires-Dist: numba >=0.59.0
Provides-Extra: all
Requires-Dist: numpy >=1.23.1 ; extra == 'all'
Requires-Dist: gymnasium >=0.27.1 ; extra == 'all'
Requires-Dist: pygame >=2.3.0 ; extra == 'all'
Requires-Dist: pettingzoo >=1.22.3 ; extra == 'all'
Requires-Dist: matplotlib ==3.8.4 ; extra == 'all'
Requires-Dist: numba >=0.59.0 ; extra == 'all'
Requires-Dist: GDAL ==3.4.1 ; extra == 'all'
Requires-Dist: opendrift ; extra == 'all'
Provides-Extra: coverage
Requires-Dist: GDAL ==3.4.1 ; extra == 'coverage'
Requires-Dist: opendrift ; extra == 'coverage'
